LICENSE
README.md
setup.py
ctrip_helper/__init__.py
ctrip_helper/config.py
ctrip_helper/http_client.py
ctrip_helper.egg-info/PKG-INFO
ctrip_helper.egg-info/SOURCES.txt
ctrip_helper.egg-info/dependency_links.txt
ctrip_helper.egg-info/requires.txt
ctrip_helper.egg-info/top_level.txt
ctrip_helper/api/__init__.py
ctrip_helper/api/desktop_ui.py
ctrip_helper/api/flight_desktop_ui.py
ctrip_helper/api/h5_ui.py
ctrip_helper/api/http_api.py